{
    "0xe9aa15a067b010a4078909bade54f0c6abcbb852": {
        "name": "Metauce",
        "description": "Metauce is a new generation P2E game with galaxy explorer and mining.",
        "links": {
            "Github": "",
            "Discord": "https://discord.gg/5c9CP6AuWs",
            "Medium": "https://medium.com/@metauce",
            "Telegram": "https://t.me/metauce",
            "Twitter": "https://twitter.com/metauce"
        },
        "website": "https://metauce.org/",
        "logo": "https://metauce.org/image/logo.png"
    }
}